dddp/__init__.py
dddp/admin.py
dddp/alea.py
dddp/api.py
dddp/apps.py
dddp/ddp.py
dddp/logging.py
dddp/main.py
dddp/models.py
dddp/postgres.py
dddp/tests.py
dddp/views.py
dddp/websocket.py
dddp/accounts/__init__.py
dddp/accounts/ddp.py
dddp/accounts/tests.py
dddp/migrations/0001_initial.py
dddp/migrations/0002_auto_20150408_0321.py
dddp/migrations/0003_auto_20150413_1328.py
dddp/migrations/0004_connection_server_addr.py
dddp/migrations/0005_auto_20150427_1209.py
dddp/migrations/0006_auto_20150428_2245.py
dddp/migrations/0007_auto_20150505_1302.py
dddp/migrations/0008_remove_subscription_publication_class.py
dddp/migrations/0009_auto_20150812_0856.py
dddp/migrations/__init__.py
dddp/test/__init__.py
dddp/test/manage.py
dddp/test/django_todos/__init__.py
dddp/test/django_todos/admin.py
dddp/test/django_todos/ddp.py
dddp/test/django_todos/models.py
dddp/test/django_todos/tests.py
dddp/test/django_todos/views.py
dddp/test/django_todos/migrations/0001_initial.py
dddp/test/django_todos/migrations/__init__.py
dddp/test/meteor_todos/meteor_todos.css
dddp/test/meteor_todos/meteor_todos.html
dddp/test/meteor_todos/meteor_todos.js
dddp/test/meteor_todos/.meteor/.finished-upgraders
dddp/test/meteor_todos/.meteor/.gitignore
dddp/test/meteor_todos/.meteor/.id
dddp/test/meteor_todos/.meteor/packages
dddp/test/meteor_todos/.meteor/platforms
dddp/test/meteor_todos/.meteor/release
dddp/test/meteor_todos/.meteor/versions
dddp/test/test_project/__init__.py
dddp/test/test_project/settings.py
dddp/test/test_project/urls.py
dddp/test/test_project/wsgi.py
django_ddp-0.19.1.dist-info/DESCRIPTION.rst
django_ddp-0.19.1.dist-info/METADATA
django_ddp-0.19.1.dist-info/RECORD
django_ddp-0.19.1.dist-info/WHEEL
django_ddp-0.19.1.dist-info/entry_points.txt
django_ddp-0.19.1.dist-info/metadata.json
django_ddp-0.19.1.dist-info/pbr.json
django_ddp-0.19.1.dist-info/top_level.txt
django_ddp-0.19.1.dist-info/zip-safe
