Metadata-Version: 2.0
Name: django-ddp
Version: 0.19.1
Summary: Django/PostgreSQL implementation of the Meteor server.
Home-page: https://github.com/django-ddp/django-ddp
Author: Tyson Clugg
Author-email: tyson@clugg.net
License: MIT
Keywords: django ddp meteor websocket websockets realtime real-time live liveupdate live-update livequery live-query
Platform: UNKNOWN
Classifier: Development Status :: 4 - Beta
Classifier: Intended Audience :: Developers
Classifier: Topic :: Database
Classifier: Topic :: Internet
Classifier: Topic :: Internet :: WWW/HTTP
Classifier: Topic :: Internet :: WWW/HTTP :: Browsers
Classifier: Topic :: Internet :: WWW/HTTP :: Dynamic Content
Classifier: Topic :: Internet :: WWW/HTTP :: Dynamic Content :: CGI Tools/Libraries
Classifier: Topic :: Internet :: WWW/HTTP :: HTTP Servers
Classifier: Topic :: Internet :: WWW/HTTP :: Session
Classifier: Topic :: Internet :: WWW/HTTP :: WSGI
Classifier: Topic :: Internet :: WWW/HTTP :: WSGI :: Server
Classifier: Topic :: Software Development :: Libraries
Classifier: Topic :: Software Development :: Object Brokering
Classifier: Topic :: System :: Distributed Computing
Classifier: License :: OSI Approved :: MIT License
Classifier: License :: DFSG approved
Classifier: License :: OSI Approved
Classifier: Programming Language :: Python
Classifier: Programming Language :: Python :: 2
Classifier: Programming Language :: Python :: 3
Classifier: Framework :: Django
Classifier: Programming Language :: Python :: 2.7
Classifier: Programming Language :: Python :: 3.2
Classifier: Programming Language :: Python :: 3.3
Classifier: Programming Language :: Python :: 3.4
Classifier: Framework :: Django :: 1.8
Classifier: Framework :: Django :: 1.9
Requires-Dist: Django (>=1.8)
Requires-Dist: meteor-ejson (>=1.0)
Requires-Dist: psycogreen (>=1.0)
Requires-Dist: pybars3 (>=0.9.1)
Requires-Dist: six (>=1.10.0)
Requires-Dist: gevent-websocket (>=0.9,!=0.9.4)
Requires-Dist: psycopg2cffi (>=2.7.2); platform_python_implementation != "CPython"
Requires-Dist: gevent (>=1.1rc2); platform_python_implementation!="CPython" or python_version>="3.0"
Requires-Dist: psycopg2 (>=2.5.4); platform_python_implementation=="CPython"
Requires-Dist: gevent (>=1.0); platform_python_implementation=="CPython" and python_version<"3.0"
Requires-Dist: Django (<1.9); python_version=="3.3"
Provides-Extra: develop
Requires-Dist: Sphinx (>=1.3.3); extra == 'develop'
Requires-Dist: Sphinx-PyPI-upload (>=0.2.1); extra == 'develop'
Requires-Dist: sphinxcontrib-dashbuilder (>=0.1.0); extra == 'develop'
Requires-Dist: twine (>=1.6.4); extra == 'develop'
